MANIFEST.in
README.md
requirements.txt
setup.py
nameapi_client/__init__.py
nameapi_client/client.py
nameapi_client/command.py
nameapi_client/utils.py
nameapi_client/ontology/__init__.py
nameapi_client/ontology/address.py
nameapi_client/ontology/age.py
nameapi_client/ontology/contact.py
nameapi_client/ontology/gender.py
nameapi_client/ontology/input_person.py
nameapi_client/ontology/name.py
nameapi_client/ontology/utils.py
nameapi_client/services/__init__.py
nameapi_client/services/email_parser.py
nameapi_client/services/person_formatter.py
nameapi_client/services/person_genderizer.py
nameapi_client/services/person_matcher.py
nameapi_client/services/person_parser.py
nameapi_client/services/risk_detector.py
nameapi_client_python.egg-info/PKG-INFO
nameapi_client_python.egg-info/SOURCES.txt
nameapi_client_python.egg-info/dependency_links.txt
nameapi_client_python.egg-info/requires.txt
nameapi_client_python.egg-info/top_level.txt
tests/__init__.py
tests/tests.py