Metadata-Version: 2.1
Name: nameapi-client-python
Version: 1.0.1
Summary: Python Client for the NameAPI Web Services
Home-page: https://www.nameapi.org/
Project-URL: Source Code, https://github.com/optimaize/nameapi-client-python
Project-URL: Bug Tracker, https://github.com/optimaize/nameapi-client-python/issues
Keywords: nameapi,rest nameapi,nameapi client,name parser,name matcher,person risk detector,name genderizer,email name parser,email parser,disposable email detector,dea detector
Classifier: Programming Language :: Python :: 3
Classifier: License :: OSI Approved :: GNU Lesser General Public License v3 (LGPLv3)
Classifier: Operating System :: OS Independent
Requires-Python: >=3.8
Requires-Dist: certifi==2024.2.2
Requires-Dist: charset-normalizer==3.3.2
Requires-Dist: idna==3.6
Requires-Dist: requests==2.31.0
Requires-Dist: urllib3==2.2.1
